djangopoweredtools/__init__.py
djangopoweredtools/forms.py
djangopoweredtools/generic.py
django_powered_tools-1.6.dist-info/METADATA
django_powered_tools-1.6.dist-info/WHEEL
django_powered_tools-1.6.dist-info/top_level.txt
django_powered_tools-1.6.dist-info/RECORD
