Metadata-Version: 2.4
Name: django-powered-tools
Version: 1.6
Summary: View'sv y herramientas extra para django que permiten busqueda sobre listas y redireccion con anclas y extras
Home-page: https://github.com/DARKDEYMON/django-powered-tools
Author: darkdeymon
Author-email: darkdeymon04@gmail.com
Requires-Dist: django>=5.1
Dynamic: author
Dynamic: author-email
Dynamic: description
Dynamic: description-content-type
Dynamic: home-page
Dynamic: requires-dist
Dynamic: summary
